smsmobileapi/__init__.py
smsmobileapi/smssender.py
smsmobileapi-2.0.1.dist-info/LICENSE
smsmobileapi-2.0.1.dist-info/METADATA
smsmobileapi-2.0.1.dist-info/WHEEL
smsmobileapi-2.0.1.dist-info/top_level.txt
smsmobileapi-2.0.1.dist-info/RECORD
