Metadata-Version: 2.1
Name: smsmobileapi
Version: 2.0.1
Summary: A module that allows sending SMS and WhatsApp for free from your own mobile phone and receiving SMS on your mobile phone, all for free since the mobile plan is used
Home-page: https://github.com/smsmobileapi/smsmobileapi
Author: Quest-Concept
Author-email: info@smsmobileapi.com
License: UNKNOWN
Platform: UNKNOWN
Classifier: Programming Language :: Python :: 3
Classifier: License :: OSI Approved :: MIT License
Classifier: Operating System :: OS Independent
Requires-Python: >=3.6
License-File: LICENSE
